{
    "version": "0.4",
    "title": "Seruni V1 &#8211; Products",
    "type": "product-archive",
    "metadata": {
        "template_type": "archive-product",
        "include_in_zip": "1",
        "elementor_pro_required": "1",
        "elementor_library_type": "product-archive",
        "elementor_pro_conditions": [
            "include\/product_archive"
        ],
        "additional_template_information": [
            "This is a \"Product Archive\" template for Elementor Pro.",
            "This template will display on: All Product Archives."
        ],
        "wp_page_template": "default"
    },
    "content": [
        {
            "id": "66908406",
            "settings": {
                "padding": {
                    "unit": "em",
                    "top": "2",
                    "right": "0",
                    "bottom": "0",
                    "left": "0",
                    "isLinked": false
                },
                "padding_tablet": {
                    "unit": "em",
                    "top": "2",
                    "right": "1",
                    "bottom": "0",
                    "left": "1",
                    "isLinked": false
                },
                "padding_mobile": {
                    "unit": "px",
                    "top": "10",
                    "right": "10",
                    "bottom": "10",
                    "left": "10",
                    "isLinked": true
                }
            },
            "elements": [
                {
                    "id": "38161d98",
                    "settings": {
                        "_column_size": 100,
                        "_inline_size": null,
                        "padding": {
                            "unit": "px",
                            "top": "0",
                            "right": "0",
                            "bottom": "0",
                            "left": "0",
                            "isLinked": false
                        }
                    },
                    "elements": [
                        {
                            "id": "c91f880",
                            "settings": {
                                "background_background": "classic",
                                "background_image": {
                                    "url": "https:\/\/fullkit.moxcreative.com\/seruni\/wp-content\/uploads\/sites\/7\/2022\/09\/happy-girl-in-luxury-earrings-smiling-and-looking-at-camera.jpg",
                                    "id": 1831,
                                    "alt": "Happy girl in luxury earrings smiling and looking at camera",
                                    "source": "library"
                                },
                                "background_position": "center center",
                                "background_repeat": "no-repeat",
                                "background_size": "cover",
                                "background_overlay_background": "gradient",
                                "background_overlay_color": "#F8F2F080",
                                "background_overlay_gradient_angle": {
                                    "unit": "deg",
                                    "size": 135,
                                    "sizes": []
                                },
                                "background_overlay_opacity": {
                                    "unit": "px",
                                    "size": 1,
                                    "sizes": []
                                },
                                "border_radius": {
                                    "unit": "px",
                                    "top": "10",
                                    "right": "10",
                                    "bottom": "10",
                                    "left": "10",
                                    "isLinked": true
                                },
                                "padding": {
                                    "unit": "em",
                                    "top": "0",
                                    "right": "2",
                                    "bottom": "0",
                                    "left": "2",
                                    "isLinked": false
                                },
                                "padding_tablet": {
                                    "unit": "em",
                                    "top": "0",
                                    "right": "2",
                                    "bottom": "0",
                                    "left": "2",
                                    "isLinked": false
                                },
                                "padding_mobile": {
                                    "unit": "em",
                                    "top": "0",
                                    "right": "1",
                                    "bottom": "0",
                                    "left": "1",
                                    "isLinked": false
                                },
                                "__globals__": {
                                    "background_overlay_color": "",
                                    "background_overlay_color_b": "globals\/colors?id=accent"
                                },
                                "animation": "fadeIn",
                                "animation_delay": 200,
                                "overflow": "hidden",
                                "background_overlay_color_b_stop": {
                                    "unit": "%",
                                    "size": 70,
                                    "sizes": []
                                },
                                "margin": {
                                    "unit": "em",
                                    "top": "0",
                                    "right": 0,
                                    "bottom": "0",
                                    "left": 0,
                                    "isLinked": false
                                },
                                "margin_tablet": {
                                    "unit": "em",
                                    "top": "",
                                    "right": "",
                                    "bottom": "",
                                    "left": "",
                                    "isLinked": true
                                },
                                "margin_mobile": {
                                    "unit": "em",
                                    "top": "",
                                    "right": "",
                                    "bottom": "",
                                    "left": "",
                                    "isLinked": true
                                }
                            },
                            "elements": [
                                {
                                    "id": "792c790f",
                                    "settings": {
                                        "_column_size": 100,
                                        "_inline_size": null,
                                        "margin": {
                                            "unit": "%",
                                            "top": "0",
                                            "right": "0",
                                            "bottom": "0",
                                            "left": "50",
                                            "isLinked": false
                                        },
                                        "margin_tablet": {
                                            "unit": "%",
                                            "top": "0",
                                            "right": "0",
                                            "bottom": "0",
                                            "left": "45",
                                            "isLinked": false
                                        },
                                        "margin_mobile": {
                                            "unit": "%",
                                            "top": "0",
                                            "right": "0",
                                            "bottom": "0",
                                            "left": "0",
                                            "isLinked": false
                                        },
                                        "padding": {
                                            "unit": "em",
                                            "top": "5",
                                            "right": "0",
                                            "bottom": "5",
                                            "left": "0",
                                            "isLinked": false
                                        },
                                        "padding_tablet": {
                                            "unit": "em",
                                            "top": "",
                                            "right": "",
                                            "bottom": "",
                                            "left": "",
                                            "isLinked": true
                                        },
                                        "padding_mobile": {
                                            "unit": "em",
                                            "top": "",
                                            "right": "",
                                            "bottom": "",
                                            "left": "",
                                            "isLinked": true
                                        }
                                    },
                                    "elements": [
                                        {
                                            "id": "1e39ed5e",
                                            "settings": {
                                                "title": "Shop",
                                                "header_size": "h1",
                                                "align": "center",
                                                "__globals__": {
                                                    "title_color": "globals\/colors?id=a291686"
                                                },
                                                "__dynamic__": []
                                            },
                                            "elements": [],
                                            "isInner": false,
                                            "widgetType": "heading",
                                            "elType": "widget"
                                        },
                                        {
                                            "id": "4a46d76d",
                                            "settings": {
                                                "title": "Frequently Asked Questions\n",
                                                "header_size": "h4",
                                                "align": "center",
                                                "__dynamic__": {
                                                    "title": "[elementor-tag id=\"26d539a\" name=\"archive-title\" settings=\"%7B%22include_context%22%3A%22%22%7D\"]"
                                                },
                                                "__globals__": {
                                                    "title_color": "globals\/colors?id=a291686"
                                                }
                                            },
                                            "elements": [],
                                            "isInner": false,
                                            "widgetType": "heading",
                                            "elType": "widget"
                                        },
                                        {
                                            "id": "8467637",
                                            "settings": {
                                                "source": "external_url",
                                                "source_external_url": {
                                                    "url": "https:\/\/assets9.lottiefiles.com\/packages\/lf20_k7jyykm9.json",
                                                    "is_external": "",
                                                    "nofollow": "",
                                                    "custom_attributes": ""
                                                },
                                                "width": {
                                                    "unit": "%",
                                                    "size": 60,
                                                    "sizes": []
                                                },
                                                "_offset_orientation_v": "end",
                                                "_offset_y_end": {
                                                    "unit": "px",
                                                    "size": -21,
                                                    "sizes": []
                                                },
                                                "width_tablet": {
                                                    "unit": "%",
                                                    "size": 85,
                                                    "sizes": []
                                                },
                                                "width_mobile": {
                                                    "unit": "%",
                                                    "size": 90,
                                                    "sizes": []
                                                },
                                                "start_point": {
                                                    "unit": "%",
                                                    "size": 0,
                                                    "sizes": []
                                                },
                                                "loop": "yes",
                                                "number_of_times": 1,
                                                "opacity": {
                                                    "unit": "px",
                                                    "size": 0.5,
                                                    "sizes": []
                                                },
                                                "opacity_hover": {
                                                    "unit": "px",
                                                    "size": 0.5,
                                                    "sizes": []
                                                },
                                                "_element_vertical_align": "center",
                                                "_position": "absolute"
                                            },
                                            "elements": [],
                                            "isInner": false,
                                            "widgetType": "lottie",
                                            "elType": "widget"
                                        }
                                    ],
                                    "isInner": true,
                                    "elType": "column"
                                }
                            ],
                            "isInner": true,
                            "elType": "section"
                        }
                    ],
                    "isInner": false,
                    "elType": "column"
                }
            ],
            "isInner": false,
            "elType": "section"
        },
        {
            "id": "5e6ddcdb",
            "settings": {
                "padding": {
                    "unit": "em",
                    "top": "3",
                    "right": "0",
                    "bottom": "7",
                    "left": "0",
                    "isLinked": false
                },
                "padding_tablet": {
                    "unit": "em",
                    "top": "",
                    "right": "",
                    "bottom": "",
                    "left": "",
                    "isLinked": true
                },
                "padding_mobile": {
                    "unit": "em",
                    "top": "",
                    "right": "",
                    "bottom": "",
                    "left": "",
                    "isLinked": true
                }
            },
            "elements": [
                {
                    "id": "b319b88",
                    "settings": {
                        "_column_size": 100,
                        "_inline_size": null
                    },
                    "elements": [
                        {
                            "id": "475fdc3d",
                            "settings": {
                                "products_related_title_text": "Related Products",
                                "products_upsells_title_text": "You may also like...",
                                "products_cross_sells_title_text": "You may be interested in...",
                                "column_gap": {
                                    "unit": "px",
                                    "size": 21,
                                    "sizes": []
                                },
                                "row_gap": {
                                    "unit": "px",
                                    "size": 42,
                                    "sizes": []
                                },
                                "align": "center",
                                "image_border_radius": {
                                    "unit": "px",
                                    "top": "10",
                                    "right": "10",
                                    "bottom": "10",
                                    "left": "10",
                                    "isLinked": true
                                },
                                "image_spacing": {
                                    "unit": "px",
                                    "size": 14,
                                    "sizes": []
                                },
                                "title_spacing": {
                                    "unit": "px",
                                    "size": 7,
                                    "sizes": []
                                },
                                "rating_spacing": {
                                    "unit": "px",
                                    "size": 7,
                                    "sizes": []
                                },
                                "button_border_radius": {
                                    "unit": "px",
                                    "top": "7",
                                    "right": "7",
                                    "bottom": "7",
                                    "left": "7",
                                    "isLinked": true
                                },
                                "automatically_align_buttons": "yes",
                                "view_cart_spacing": {
                                    "unit": "px",
                                    "size": 14,
                                    "sizes": []
                                },
                                "box_border_radius": {
                                    "unit": "px",
                                    "size": 10,
                                    "sizes": []
                                },
                                "box_padding": {
                                    "unit": "em",
                                    "top": "1",
                                    "right": "1",
                                    "bottom": "2",
                                    "left": "1",
                                    "isLinked": false
                                },
                                "box_padding_tablet": {
                                    "unit": "em",
                                    "top": "",
                                    "right": "",
                                    "bottom": "",
                                    "left": "",
                                    "isLinked": true
                                },
                                "box_padding_mobile": {
                                    "unit": "em",
                                    "top": "",
                                    "right": "",
                                    "bottom": "",
                                    "left": "",
                                    "isLinked": true
                                },
                                "box_bg_color": "#02010100",
                                "nothing_found_message": "It seems we can&#039;t find what you&#039;re looking for.",
                                "__globals__": {
                                    "title_typography_typography": "globals\/typography?id=520c191",
                                    "star_color": "globals\/colors?id=secondary",
                                    "empty_star_color": "globals\/colors?id=accent",
                                    "price_typography_typography": "globals\/typography?id=text",
                                    "price_color": "globals\/colors?id=primary",
                                    "button_typography_typography": "globals\/typography?id=69c152f",
                                    "button_text_color": "globals\/colors?id=a291686",
                                    "button_background_color": "globals\/colors?id=accent",
                                    "button_hover_color": "globals\/colors?id=a291686",
                                    "button_hover_background_color": "globals\/colors?id=primary",
                                    "view_cart_typography_typography": "globals\/typography?id=520c191",
                                    "box_bg_color_hover": "globals\/colors?id=91455cb",
                                    "onsale_text_color": "globals\/colors?id=a291686",
                                    "onsale_text_background_color": "globals\/colors?id=accent"
                                },
                                "show_result_count": ""
                            },
                            "elements": [],
                            "isInner": false,
                            "widgetType": "wc-archive-products",
                            "elType": "widget"
                        }
                    ],
                    "isInner": false,
                    "elType": "column"
                }
            ],
            "isInner": false,
            "elType": "section"
        },
        {
            "id": "57f4879b",
            "settings": {
                "content_width": {
                    "unit": "px",
                    "size": 720,
                    "sizes": []
                },
                "background_background": "classic",
                "background_image": {
                    "url": "https:\/\/fullkit.moxcreative.com\/seruni\/wp-content\/uploads\/sites\/7\/2022\/09\/luxury-gold-jewelry-on-set-holders-and-in-jewelry-box-on-light-dressing-table-and-wardrobe-shelves-3.jpg",
                    "id": 1800,
                    "alt": "Luxury gold jewelry on set holders and in jewelry box on light dressing table and wardrobe shelves",
                    "source": "library"
                },
                "background_position": "center center",
                "background_repeat": "no-repeat",
                "background_size": "cover",
                "background_overlay_background": "gradient",
                "background_overlay_gradient_angle": {
                    "unit": "deg",
                    "size": 135,
                    "sizes": []
                },
                "background_overlay_opacity": {
                    "unit": "px",
                    "size": 0.59999999999999997779553950749686919152736663818359375,
                    "sizes": []
                },
                "padding": {
                    "unit": "em",
                    "top": "7",
                    "right": "0",
                    "bottom": "7",
                    "left": "0",
                    "isLinked": false
                },
                "padding_tablet": {
                    "unit": "em",
                    "top": "3",
                    "right": "0",
                    "bottom": "3",
                    "left": "0",
                    "isLinked": false
                },
                "padding_mobile": {
                    "unit": "em",
                    "top": "1",
                    "right": "0",
                    "bottom": "1",
                    "left": "0",
                    "isLinked": false
                },
                "__globals__": {
                    "background_overlay_color": "globals\/colors?id=91455cb",
                    "background_overlay_color_b": "globals\/colors?id=accent"
                }
            },
            "elements": [
                {
                    "id": "12034132",
                    "settings": {
                        "_column_size": 100,
                        "_inline_size": null,
                        "padding": {
                            "unit": "em",
                            "top": "2",
                            "right": "2",
                            "bottom": "2",
                            "left": "2",
                            "isLinked": true
                        },
                        "padding_tablet": {
                            "unit": "em",
                            "top": "",
                            "right": "",
                            "bottom": "",
                            "left": "",
                            "isLinked": true
                        },
                        "padding_mobile": {
                            "unit": "em",
                            "top": "",
                            "right": "",
                            "bottom": "",
                            "left": "",
                            "isLinked": true
                        },
                        "animation": "fadeIn",
                        "animation_delay": 200
                    },
                    "elements": [
                        {
                            "id": "20e2e675",
                            "settings": {
                                "title": "Promo",
                                "header_size": "h6",
                                "align": "center",
                                "__globals__": {
                                    "title_color": "globals\/colors?id=secondary"
                                }
                            },
                            "elements": [],
                            "isInner": false,
                            "widgetType": "heading",
                            "elType": "widget"
                        },
                        {
                            "id": "73edfad1",
                            "settings": {
                                "title": "Discount up to 30% for your first purchase.",
                                "header_size": "div",
                                "align": "center",
                                "__globals__": {
                                    "typography_typography": "globals\/typography?id=primary",
                                    "title_color": "globals\/colors?id=secondary"
                                }
                            },
                            "elements": [],
                            "isInner": false,
                            "widgetType": "heading",
                            "elType": "widget"
                        },
                        {
                            "id": "11bece6",
                            "settings": {
                                "align": "center",
                                "__globals__": {
                                    "text_color": "globals\/colors?id=secondary"
                                }
                            },
                            "elements": [],
                            "isInner": false,
                            "widgetType": "text-editor",
                            "elType": "widget"
                        },
                        {
                            "id": "5e52a010",
                            "settings": {
                                "text": "Claim Promo",
                                "align": "center",
                                "size": "md",
                                "__globals__": {
                                    "button_text_color": "globals\/colors?id=accent",
                                    "background_color": "globals\/colors?id=91455cb",
                                    "hover_color": "globals\/colors?id=text",
                                    "button_background_hover_color": "globals\/colors?id=a291686"
                                }
                            },
                            "elements": [],
                            "isInner": false,
                            "widgetType": "button",
                            "elType": "widget"
                        }
                    ],
                    "isInner": false,
                    "elType": "column"
                }
            ],
            "isInner": false,
            "elType": "section"
        },
        {
            "id": "7c54ab48",
            "settings": {
                "background_background": "classic",
                "background_image": {
                    "url": "https:\/\/fullkit.moxcreative.com\/seruni\/wp-content\/uploads\/sites\/7\/2022\/07\/bg_img.png",
                    "id": 1785,
                    "alt": "",
                    "source": "library"
                },
                "background_overlay_background": "gradient",
                "background_overlay_color": "#FEFBFB2B",
                "background_overlay_color_b": "#FEFBFB",
                "background_overlay_color_b_stop": {
                    "unit": "%",
                    "size": 75,
                    "sizes": []
                },
                "background_overlay_gradient_type": "radial",
                "background_overlay_gradient_position": "bottom center",
                "background_overlay_opacity": {
                    "unit": "px",
                    "size": 1,
                    "sizes": []
                },
                "padding": {
                    "unit": "em",
                    "top": "5",
                    "right": "0",
                    "bottom": "7",
                    "left": "0",
                    "isLinked": false
                },
                "padding_tablet": {
                    "unit": "em",
                    "top": "1",
                    "right": "0",
                    "bottom": "6",
                    "left": "0",
                    "isLinked": false
                },
                "padding_mobile": {
                    "unit": "em",
                    "top": "1",
                    "right": "0",
                    "bottom": "4",
                    "left": "0",
                    "isLinked": false
                },
                "__globals__": {
                    "background_overlay_color": "",
                    "background_overlay_color_b": "globals\/colors?id=308e809"
                }
            },
            "elements": [
                {
                    "id": "5ac94b77",
                    "settings": {
                        "_column_size": 100,
                        "_inline_size": null,
                        "padding": {
                            "unit": "px",
                            "top": "0",
                            "right": "0",
                            "bottom": "0",
                            "left": "0",
                            "isLinked": false
                        }
                    },
                    "elements": [
                        {
                            "id": "631bfbe7",
                            "settings": {
                                "content_width": {
                                    "unit": "px",
                                    "size": 720,
                                    "sizes": []
                                }
                            },
                            "elements": [
                                {
                                    "id": "46c5644d",
                                    "settings": {
                                        "_column_size": 100,
                                        "_inline_size": null,
                                        "padding": {
                                            "unit": "em",
                                            "top": "2",
                                            "right": "2",
                                            "bottom": "2",
                                            "left": "2",
                                            "isLinked": true
                                        },
                                        "padding_tablet": {
                                            "unit": "em",
                                            "top": "",
                                            "right": "",
                                            "bottom": "",
                                            "left": "",
                                            "isLinked": true
                                        },
                                        "padding_mobile": {
                                            "unit": "em",
                                            "top": "",
                                            "right": "",
                                            "bottom": "",
                                            "left": "",
                                            "isLinked": true
                                        },
                                        "animation": "fadeInUp"
                                    },
                                    "elements": [
                                        {
                                            "id": "3ae7f397",
                                            "settings": {
                                                "title": "Need more help?",
                                                "align": "center"
                                            },
                                            "elements": [],
                                            "isInner": false,
                                            "widgetType": "heading",
                                            "elType": "widget"
                                        },
                                        {
                                            "id": "7b4fced6",
                                            "settings": {
                                                "align": "center"
                                            },
                                            "elements": [],
                                            "isInner": false,
                                            "widgetType": "text-editor",
                                            "elType": "widget"
                                        }
                                    ],
                                    "isInner": true,
                                    "elType": "column"
                                }
                            ],
                            "isInner": true,
                            "elType": "section"
                        },
                        {
                            "id": "2cbb7feb",
                            "settings": {
                                "structure": "30"
                            },
                            "elements": [
                                {
                                    "id": "653a79d7",
                                    "settings": {
                                        "_column_size": 33,
                                        "_inline_size": null,
                                        "background_background": "classic",
                                        "border_radius": {
                                            "unit": "px",
                                            "top": "10",
                                            "right": "10",
                                            "bottom": "10",
                                            "left": "10",
                                            "isLinked": true
                                        },
                                        "margin": {
                                            "unit": "px",
                                            "top": "10",
                                            "right": "10",
                                            "bottom": "10",
                                            "left": "10",
                                            "isLinked": true
                                        },
                                        "padding": {
                                            "unit": "em",
                                            "top": "2",
                                            "right": "2",
                                            "bottom": "2",
                                            "left": "2",
                                            "isLinked": true
                                        },
                                        "padding_tablet": {
                                            "unit": "em",
                                            "top": "2",
                                            "right": "1",
                                            "bottom": "2",
                                            "left": "1",
                                            "isLinked": false
                                        },
                                        "padding_mobile": {
                                            "unit": "em",
                                            "top": "2",
                                            "right": "2",
                                            "bottom": "2",
                                            "left": "2",
                                            "isLinked": true
                                        },
                                        "animation": "fadeInUp",
                                        "animation_delay": 200,
                                        "__globals__": {
                                            "background_color": "globals\/colors?id=91455cb"
                                        }
                                    },
                                    "elements": [
                                        {
                                            "id": "38583d01",
                                            "settings": {
                                                "selected_icon": {
                                                    "value": "icon icon-Support-2",
                                                    "library": "ekiticons"
                                                },
                                                "title_text": "Customer Service",
                                                "description_text": "Bibendum dictumst morbi risus in augue himenaeos nunc nisl faucibus",
                                                "title_size": "h5",
                                                "icon_space": {
                                                    "unit": "px",
                                                    "size": 14,
                                                    "sizes": []
                                                },
                                                "icon_size": {
                                                    "unit": "px",
                                                    "size": 42,
                                                    "sizes": []
                                                },
                                                "title_bottom_space": {
                                                    "unit": "px",
                                                    "size": 7,
                                                    "sizes": []
                                                },
                                                "__globals__": {
                                                    "primary_color": "globals\/colors?id=accent"
                                                }
                                            },
                                            "elements": [],
                                            "isInner": false,
                                            "widgetType": "icon-box",
                                            "elType": "widget"
                                        },
                                        {
                                            "id": "5f982950",
                                            "settings": {
                                                "text": "Chat now",
                                                "align": "center"
                                            },
                                            "elements": [],
                                            "isInner": false,
                                            "widgetType": "button",
                                            "elType": "widget"
                                        }
                                    ],
                                    "isInner": true,
                                    "elType": "column"
                                },
                                {
                                    "id": "f7453bd",
                                    "settings": {
                                        "_column_size": 33,
                                        "_inline_size": null,
                                        "background_background": "classic",
                                        "border_radius": {
                                            "unit": "px",
                                            "top": "10",
                                            "right": "10",
                                            "bottom": "10",
                                            "left": "10",
                                            "isLinked": true
                                        },
                                        "margin": {
                                            "unit": "px",
                                            "top": "10",
                                            "right": "10",
                                            "bottom": "10",
                                            "left": "10",
                                            "isLinked": true
                                        },
                                        "padding": {
                                            "unit": "em",
                                            "top": "2",
                                            "right": "2",
                                            "bottom": "2",
                                            "left": "2",
                                            "isLinked": true
                                        },
                                        "padding_tablet": {
                                            "unit": "em",
                                            "top": "2",
                                            "right": "1",
                                            "bottom": "2",
                                            "left": "1",
                                            "isLinked": false
                                        },
                                        "padding_mobile": {
                                            "unit": "em",
                                            "top": "2",
                                            "right": "2",
                                            "bottom": "2",
                                            "left": "2",
                                            "isLinked": true
                                        },
                                        "animation": "fadeInUp",
                                        "__globals__": {
                                            "background_color": "globals\/colors?id=91455cb"
                                        }
                                    },
                                    "elements": [
                                        {
                                            "id": "2a167ffa",
                                            "settings": {
                                                "selected_icon": {
                                                    "value": "icon icon-email",
                                                    "library": "ekiticons"
                                                },
                                                "title_text": "Send Ticket",
                                                "description_text": "Bibendum dictumst morbi risus in augue himenaeos nunc nisl faucibus",
                                                "title_size": "h5",
                                                "icon_space": {
                                                    "unit": "px",
                                                    "size": 14,
                                                    "sizes": []
                                                },
                                                "icon_size": {
                                                    "unit": "px",
                                                    "size": 42,
                                                    "sizes": []
                                                },
                                                "title_bottom_space": {
                                                    "unit": "px",
                                                    "size": 7,
                                                    "sizes": []
                                                },
                                                "__globals__": {
                                                    "primary_color": "globals\/colors?id=accent"
                                                }
                                            },
                                            "elements": [],
                                            "isInner": false,
                                            "widgetType": "icon-box",
                                            "elType": "widget"
                                        },
                                        {
                                            "id": "356bc3a5",
                                            "settings": {
                                                "text": "Contact us",
                                                "align": "center"
                                            },
                                            "elements": [],
                                            "isInner": false,
                                            "widgetType": "button",
                                            "elType": "widget"
                                        }
                                    ],
                                    "isInner": true,
                                    "elType": "column"
                                },
                                {
                                    "id": "725f26b4",
                                    "settings": {
                                        "_column_size": 33,
                                        "_inline_size": null,
                                        "background_background": "classic",
                                        "border_radius": {
                                            "unit": "px",
                                            "top": "10",
                                            "right": "10",
                                            "bottom": "10",
                                            "left": "10",
                                            "isLinked": true
                                        },
                                        "margin": {
                                            "unit": "px",
                                            "top": "10",
                                            "right": "10",
                                            "bottom": "10",
                                            "left": "10",
                                            "isLinked": true
                                        },
                                        "padding": {
                                            "unit": "em",
                                            "top": "2",
                                            "right": "2",
                                            "bottom": "2",
                                            "left": "2",
                                            "isLinked": true
                                        },
                                        "padding_tablet": {
                                            "unit": "em",
                                            "top": "2",
                                            "right": "1",
                                            "bottom": "2",
                                            "left": "1",
                                            "isLinked": false
                                        },
                                        "padding_mobile": {
                                            "unit": "em",
                                            "top": "2",
                                            "right": "2",
                                            "bottom": "2",
                                            "left": "2",
                                            "isLinked": true
                                        },
                                        "animation": "fadeInUp",
                                        "animation_delay": 400,
                                        "__globals__": {
                                            "background_color": "globals\/colors?id=91455cb"
                                        }
                                    },
                                    "elements": [
                                        {
                                            "id": "2ab451a1",
                                            "settings": {
                                                "selected_icon": {
                                                    "value": "icon icon-open-book1",
                                                    "library": "ekiticons"
                                                },
                                                "title_text": "News & Article",
                                                "description_text": "Bibendum dictumst morbi risus in augue himenaeos nunc nisl faucibus",
                                                "title_size": "h5",
                                                "icon_space": {
                                                    "unit": "px",
                                                    "size": 14,
                                                    "sizes": []
                                                },
                                                "icon_size": {
                                                    "unit": "px",
                                                    "size": 42,
                                                    "sizes": []
                                                },
                                                "title_bottom_space": {
                                                    "unit": "px",
                                                    "size": 7,
                                                    "sizes": []
                                                },
                                                "__globals__": {
                                                    "primary_color": "globals\/colors?id=accent"
                                                }
                                            },
                                            "elements": [],
                                            "isInner": false,
                                            "widgetType": "icon-box",
                                            "elType": "widget"
                                        },
                                        {
                                            "id": "77f8b391",
                                            "settings": {
                                                "text": "Read Now",
                                                "align": "center"
                                            },
                                            "elements": [],
                                            "isInner": false,
                                            "widgetType": "button",
                                            "elType": "widget"
                                        }
                                    ],
                                    "isInner": true,
                                    "elType": "column"
                                }
                            ],
                            "isInner": true,
                            "elType": "section"
                        }
                    ],
                    "isInner": false,
                    "elType": "column"
                }
            ],
            "isInner": false,
            "elType": "section"
        }
    ],
    "page_settings": {
        "scroll_snap": "yes",
        "force_stop": "always"
    }
}